{
  "_class": "symbolInstance",
  "booleanOperation": -1,
  "clippingMaskMode": 0,
  "do_objectID": "6BE0F9BA-539D-4C86-9D08-8E8D4EFE5094",
  "exportOptions": {
    "_class": "exportOptions",
    "exportFormats": [
    ],
    "includedLayerIds": [
    ],
    "layerOptions": 0,
    "shouldTrim": false
  },
  "frame": {
    "_class": "rect",
    "constrainProportions": false,
    "height": 270,
    "width": 265,
    "x": 940,
    "y": 972
  },
  "hasClippingMask": false,
  "horizontalSpacing": 0,
  "isFixedToViewport": false,
  "isFlippedHorizontal": false,
  "isFlippedVertical": false,
  "isLocked": false,
  "isVisible": true,
  "layerListExpandedType": 0,
  "name": "Group 5 Copy 7",
  "nameIsFixed": false,
  "overrideValues": [
    {
      "_class": "overrideValue",
      "do_objectID": "800C6ED9-0F42-4F7A-93FA-A649105D3E8F",
      "overrideName": "996112A0-AE37-4C15-A8E3-8B5BFEB8432F_image",
      "value": {
        "_class": "MSJSONFileReference",
        "_ref": "images/58fb8a28f4a0bbe19d253e6202c1a0c79d5ec9f6.png",
        "_ref_class": "MSImageData"
      }
    }
  ],
  "resizingConstraint": 63,
  "resizingType": 0,
  "rotation": 0,
  "scale": 1,
  "shouldBreakMaskChain": false,
  "style": {
    "_class": "style",
    "endMarkerType": 0,
    "miterLimit": 10,
    "startMarkerType": 0,
    "windingRule": 1
  },
  "symbolID": "053D651E-3513-4F56-9CDA-9B0C809DDBE2",
  "verticalSpacing": 0
}