{
  "_class": "symbolInstance",
  "booleanOperation": -1,
  "clippingMaskMode": 0,
  "do_objectID": "65918CC6-1E05-40A1-B9D7-7512947C1CBE",
  "exportOptions": {
    "_class": "exportOptions",
    "do_objectID": "A4838BEB-02E3-4C5F-B37C-8CDB3D104D83",
    "exportFormats": [
    ],
    "includedLayerIds": [
    ],
    "layerOptions": 0,
    "shouldTrim": false
  },
  "frame": {
    "_class": "rect",
    "constrainProportions": false,
    "do_objectID": "68B012B1-A706-43AA-98E7-728CEC7816EC",
    "height": 17,
    "width": 58,
    "x": 122,
    "y": 0
  },
  "hasClippingMask": false,
  "horizontalSpacing": 0,
  "isFixedToViewport": false,
  "isFlippedHorizontal": false,
  "isFlippedVertical": false,
  "isLocked": false,
  "isVisible": true,
  "layerListExpandedType": 0,
  "name": "Group 12",
  "nameIsFixed": false,
  "overrideValues": [
    {
      "_class": "overrideValue",
      "overrideName": "E72965FD-2367-4533-9CEE-2F5D77AA5529_stringValue",
      "value": "文化活动"
    }
  ],
  "resizingConstraint": 63,
  "resizingType": 0,
  "rotation": 0,
  "scale": 1,
  "shouldBreakMaskChain": false,
  "style": {
    "_class": "style",
    "do_objectID": "7C2DDE3D-7489-4E63-923A-40ACB70AC856",
    "endMarkerType": 0,
    "miterLimit": 10,
    "startMarkerType": 0,
    "windingRule": 1
  },
  "symbolID": "1D8F6F25-6774-4B7D-BBDA-748FC511D66D",
  "verticalSpacing": 0
}