{
  "_class": "group",
  "booleanOperation": -1,
  "clippingMaskMode": 0,
  "do_objectID": "66F4A957-7657-4924-9DE1-DB1290F859B4",
  "exportOptions": {
    "_class": "exportOptions",
    "do_objectID": "94E5F62C-97B6-4003-876D-F19AD7550CC4",
    "exportFormats": [
    ],
    "includedLayerIds": [
    ],
    "layerOptions": 0,
    "shouldTrim": false
  },
  "frame": {
    "_class": "rect",
    "constrainProportions": false,
    "do_objectID": "95C46821-B196-4DAB-B292-89569B72DF47",
    "height": 540,
    "width": 1920,
    "x": 0,
    "y": 0
  },
  "hasClickThrough": false,
  "hasClippingMask": false,
  "isFixedToViewport": false,
  "isFlippedHorizontal": false,
  "isFlippedVertical": false,
  "isLocked": false,
  "isVisible": true,
  "layerListExpandedType": 0,
  "layers": [
    {
      "class": "rectangle",
      "id": "83A438E6-50DE-4963-BBB6-8C1DC2EEB2CD"
    },
    {
      "class": "bitmap",
      "id": "4A3910A9-29E4-4E0E-B853-95B9EF24D0DA"
    }
  ],
  "name": "500565596_banner",
  "nameIsFixed": false,
  "resizingConstraint": 63,
  "resizingType": 0,
  "rotation": 0,
  "shouldBreakMaskChain": false,
  "style": {
    "_class": "style",
    "do_objectID": "0D8A28FF-5009-4629-8729-9183E81390B3",
    "endMarkerType": 0,
    "miterLimit": 10,
    "startMarkerType": 0,
    "windingRule": 1
  }
}